pygear3/__init__.py
pygear3/global_v.py
pygear3/core/AsyncManager.py
pygear3/core/Command.py
pygear3/core/Gear.py
pygear3/core/Global.py
pygear3/core/MQTTConnector.py
pygear3/core/Router.py
pygear3/core/WorkerBase.py
pygear3/core/__init__.py
pygear3/model/Item.py
pygear3/model/__init__.py
pygear3/worker/MQTTWorker.py
pygear3/worker/__init__.py
pygear3-0.0.3.dist-info/LICENSE
pygear3-0.0.3.dist-info/METADATA
pygear3-0.0.3.dist-info/WHEEL
pygear3-0.0.3.dist-info/top_level.txt
pygear3-0.0.3.dist-info/RECORD
