Metadata-Version: 2.1
Name: pygear3
Version: 0.0.3
Summary: UNKNOWN
Home-page: http://gitee.com/shellvv/pygear3
Author: shellvv
Author-email: shellvv@yeah.com
License: UNKNOWN
Platform: UNKNOWN
Classifier: Programming Language :: Python :: 3
Classifier: License :: OSI Approved :: MIT License
Classifier: Operating System :: OS Independent
Requires-Dist: pyhelper3
Requires-Dist: pyyaml
Requires-Dist: paho.mqtt
